micro_update_manager/__init__.py
micro_update_manager/config_loader.py
micro_update_manager/micro_update_manager.py
micro_update_manager/package_updater.py
micro_update_manager/process_manager.py
micro_update_manager/interfaces/__init__.py
micro_update_manager/interfaces/grpc_interface.py
micro_update_manager/interfaces/http_interface.py
micro_update_manager/interfaces/rest_interface.py
tests/__init__.py
tests/example_config.yaml
tests/test_config_loader.py
tests/test_http_interface.py
tests/test_micro_update_manager.py
tests/test_package_updater.py
tests/test_process_manager.py
micro_update_manager-0.1.1.dist-info/LICENSE
micro_update_manager-0.1.1.dist-info/METADATA
micro_update_manager-0.1.1.dist-info/WHEEL
micro_update_manager-0.1.1.dist-info/entry_points.txt
micro_update_manager-0.1.1.dist-info/top_level.txt
micro_update_manager-0.1.1.dist-info/RECORD
