Metadata-Version: 2.1
Name: micro-update-manager
Version: 0.1.1
Summary: A Python package for monitoring and updating Python packages, managing and restarting dependent microservices.
Home-page: https://github.com/AleksanderStanikHE/micro-update-manager.git
Author: Aleksander Stanik (Olek)
Author-email: aleksander.stanik@hammerheadsengineers.com
Classifier: Programming Language :: Python :: 3
Classifier: License :: OSI Approved :: MIT License
Classifier: Operating System :: OS Independent
Requires-Python: >=3.7
License-File: LICENSE
Requires-Dist: flake8
Requires-Dist: numpy
Requires-Dist: requests
Requires-Dist: pyyaml
